odoo8_addon_stock_quant_partner_info-8.0.1.1.0.99.dev5-py3.8-nspkg.pth
odoo_addons/stock_quant_partner_info/README.rst
odoo_addons/stock_quant_partner_info/__init__.py
odoo_addons/stock_quant_partner_info/__openerp__.py
odoo_addons/stock_quant_partner_info/i18n/am.po
odoo_addons/stock_quant_partner_info/i18n/ar.po
odoo_addons/stock_quant_partner_info/i18n/bg.po
odoo_addons/stock_quant_partner_info/i18n/bs.po
odoo_addons/stock_quant_partner_info/i18n/ca.po
odoo_addons/stock_quant_partner_info/i18n/cs.po
odoo_addons/stock_quant_partner_info/i18n/da.po
odoo_addons/stock_quant_partner_info/i18n/de.po
odoo_addons/stock_quant_partner_info/i18n/el_GR.po
odoo_addons/stock_quant_partner_info/i18n/en_GB.po
odoo_addons/stock_quant_partner_info/i18n/es.po
odoo_addons/stock_quant_partner_info/i18n/es_CR.po
odoo_addons/stock_quant_partner_info/i18n/es_EC.po
odoo_addons/stock_quant_partner_info/i18n/es_MX.po
odoo_addons/stock_quant_partner_info/i18n/es_VE.po
odoo_addons/stock_quant_partner_info/i18n/et.po
odoo_addons/stock_quant_partner_info/i18n/fi.po
odoo_addons/stock_quant_partner_info/i18n/fr.po
odoo_addons/stock_quant_partner_info/i18n/fr_CA.po
odoo_addons/stock_quant_partner_info/i18n/fr_CH.po
odoo_addons/stock_quant_partner_info/i18n/fr_FR.po
odoo_addons/stock_quant_partner_info/i18n/gl.po
odoo_addons/stock_quant_partner_info/i18n/hr.po
odoo_addons/stock_quant_partner_info/i18n/hr_HR.po
odoo_addons/stock_quant_partner_info/i18n/hu.po
odoo_addons/stock_quant_partner_info/i18n/id.po
odoo_addons/stock_quant_partner_info/i18n/it.po
odoo_addons/stock_quant_partner_info/i18n/ja.po
odoo_addons/stock_quant_partner_info/i18n/lt.po
odoo_addons/stock_quant_partner_info/i18n/lv.po
odoo_addons/stock_quant_partner_info/i18n/mk.po
odoo_addons/stock_quant_partner_info/i18n/mn.po
odoo_addons/stock_quant_partner_info/i18n/nb.po
odoo_addons/stock_quant_partner_info/i18n/nb_NO.po
odoo_addons/stock_quant_partner_info/i18n/nl.po
odoo_addons/stock_quant_partner_info/i18n/nl_BE.po
odoo8_addon_stock_quant_partner_info-8.0.1.1.0.99.dev5.dist-info/METADATA
odoo8_addon_stock_quant_partner_info-8.0.1.1.0.99.dev5.dist-info/WHEEL
odoo8_addon_stock_quant_partner_info-8.0.1.1.0.99.dev5.dist-info/namespace_packages.txt
odoo8_addon_stock_quant_partner_info-8.0.1.1.0.99.dev5.dist-info/top_level.txt
odoo8_addon_stock_quant_partner_info-8.0.1.1.0.99.dev5.dist-info/RECORD
